Metadata-Version: 2.1
Name: scons-tool-kpsewhich
Version: 0.2.0
Summary: KpseWhich tool for SCons
Home-page: https://github.com/ptomulik/scons-tool-kpsewhich
Author: Paweł Tomulik
Author-email: ptomulik@meil.pw.edu.pl
License: UNKNOWN
Platform: UNKNOWN
Requires-Python: >=2.7
